cravision/__init__.py
cravision/datasets/__init__.py
cravision/datasets/mnist.py
cravision/datasets/vision.py
cravision-0.0.1.dist-info/LICENSE
cravision-0.0.1.dist-info/METADATA
cravision-0.0.1.dist-info/WHEEL
cravision-0.0.1.dist-info/top_level.txt
cravision-0.0.1.dist-info/RECORD
