Metadata-Version: 2.1
Name: cravision
Version: 0.0.1
Summary: Computer vision using CraNet.
Home-page: https://github.com/shizuku/cravision
Author: shizuku
Author-email: 2112165916@qq.com
License: UNKNOWN
Project-URL: Bug Tracker, https://github.com/shizuku/cravision/issues
Platform: UNKNOWN
Classifier: Programming Language :: Python :: 3
Classifier: License :: OSI Approved :: MIT License
Classifier: Operating System :: OS Independent
Requires-Python: >=3.6
License-File: LICENSE
